cdk_hugo_deploy/__init__.py
cdk_hugo_deploy/py.typed
cdk_hugo_deploy/_jsii/__init__.py
cdk_hugo_deploy/_jsii/cdk-hugo-deploy@0.0.443.jsii.tgz
cdk_hugo_deploy-0.0.443.dist-info/LICENSE
cdk_hugo_deploy-0.0.443.dist-info/METADATA
cdk_hugo_deploy-0.0.443.dist-info/WHEEL
cdk_hugo_deploy-0.0.443.dist-info/top_level.txt
cdk_hugo_deploy-0.0.443.dist-info/RECORD
