Metadata-Version: 2.1
Name: cdk-hugo-deploy
Version: 0.0.443
Summary: Deploy Hugo static websites to AWS
Home-page: https://github.com/maafk/cdk-hugo-deploy.git
Author: Taylor Ondrey<taylor@taylorondrey.com>
License: Apache-2.0
Project-URL: Source, https://github.com/maafk/cdk-hugo-deploy.git
Classifier: Intended Audience :: Developers
Classifier: Operating System :: OS Independent
Classifier: Programming Language :: JavaScript
Classifier: Programming Language :: Python :: 3 :: Only
Classifier: Programming Language :: Python :: 3.8
Classifier: Programming Language :: Python :: 3.9
Classifier: Programming Language :: Python :: 3.10
Classifier: Programming Language :: Python :: 3.11
Classifier: Typing :: Typed
Classifier: Development Status :: 5 - Production/Stable
Classifier: License :: OSI Approved
Requires-Python: ~=3.8
License-File: LICENSE
Requires-Dist: aws-cdk-lib <3.0.0,>=2.25.0
Requires-Dist: constructs <11.0.0,>=10.0.5
Requires-Dist: jsii <2.0.0,>=1.95.0
Requires-Dist: publication >=0.0.3
Requires-Dist: typeguard ~=2.13.3
